[{"id":"8edb4e34.673db","type":"tab","label":"Wake up","disabled":false,"info":""},{"id":"9af02288.f1339","type":"tab","label":"Night light","disabled":false,"info":""},{"id":"8d2a5b3.c3ffca8","type":"tab","label":"Rob the Roborock","disabled":false,"info":""},{"id":"9e74f251.0dfb4","type":"server","z":"","name":"Home Assistant","addon":true},{"id":"4a69237f.8973ec","type":"ui_base","theme":{"name":"theme-light","lightTheme":{"default":"#0094CE","baseColor":"#0094CE","baseFont":"-apple-system,BlinkMacSystemFont,Segoe UI,Roboto,Oxygen-Sans,Ubuntu,Cantarell,Helvetica Neue,sans-serif","edited":true,"reset":false},"darkTheme":{"default":"#097479","baseColor":"#097479","baseFont":"-apple-system,BlinkMacSystemFont,Segoe UI,Roboto,Oxygen-Sans,Ubuntu,Cantarell,Helvetica Neue,sans-serif","edited":false},"customTheme":{"name":"Untitled Theme 1","default":"#4B7930","baseColor":"#4B7930","baseFont":"-apple-system,BlinkMacSystemFont,Segoe UI,Roboto,Oxygen-Sans,Ubuntu,Cantarell,Helvetica Neue,sans-serif"},"themeState":{"base-color":{"default":"#0094CE","value":"#0094CE","edited":false},"page-titlebar-backgroundColor":{"value":"#0094CE","edited":false},"page-backgroundColor":{"value":"#fafafa","edited":false},"page-sidebar-backgroundColor":{"value":"#ffffff","edited":false},"group-textColor":{"value":"#1bbfff","edited":false},"group-borderColor":{"value":"#ffffff","edited":false},"group-backgroundColor":{"value":"#ffffff","edited":false},"widget-textColor":{"value":"#111111","edited":false},"widget-backgroundColor":{"value":"#0094ce","edited":false},"widget-borderColor":{"value":"#ffffff","edited":false},"base-font":{"value":"-apple-system,BlinkMacSystemFont,Segoe UI,Roboto,Oxygen-Sans,Ubuntu,Cantarell,Helvetica Neue,sans-serif"}},"angularTheme":{"primary":"indigo","accents":"blue","warn":"red","background":"grey"}},"site":{"name":"Node-RED Dashboard","hideToolbar":"false","allowSwipe":"false","lockMenu":"false","allowTempTheme":"true","dateFormat":"DD/MM/YYYY","sizes":{"sx":48,"sy":48,"gx":6,"gy":6,"cx":6,"cy":6,"px":0,"py":0}}},{"id":"bb457b9d.eaba78","type":"server-state-changed","z":"8edb4e34.673db","name":"Monday Time","server":"9e74f251.0dfb4","version":1,"exposeToHomeAssistant":false,"haConfig":[{"property":"name","value":""},{"property":"icon","value":""}],"entityidfilter":"input_datetime.monday_time","entityidfiltertype":"exact","outputinitially":true,"state_type":"str","haltifstate":"","halt_if_type":"str","halt_if_compare":"is","outputs":1,"output_only_on_state_change":true,"for":0,"forType":"num","forUnits":"minutes","ignorePrevStateNull":false,"ignorePrevStateUnknown":false,"ignorePrevStateUnavailable":false,"ignoreCurrentStateUnknown":false,"ignoreCurrentStateUnavailable":false,"x":150,"y":200,"wires":[["92c8eb7d.4d77b8"]]},{"id":"3756e56e.8b317a","type":"schedex","z":"8edb4e34.673db","name":"Monday","passthroughunhandled":false,"suspended":false,"lat":"","lon":"","ontime":"","ontopic":"","onpayload":"open","onoffset":0,"onrandomoffset":0,"offtime":"","offtopic":"","offpayload":"","offoffset":"60","offrandomoffset":0,"mon":true,"tue":false,"wed":false,"thu":false,"fri":false,"sat":false,"sun":false,"x":500,"y":180,"wires":[["b13ab16a.b4994"]]},{"id":"92c8eb7d.4d77b8","type":"function","z":"8edb4e34.673db","name":"Parse time","func":"new_msg = {\n    payload: {\n        ontime: msg.payload.substr(0,5),\n        offtime: msg.payload.substr(0,5)\n    }\n}\nreturn new_msg;","outputs":1,"noerr":0,"initialize":"","finalize":"","x":330,"y":200,"wires":[["3756e56e.8b317a"]]},{"id":"61b4e730.1fe2e8","type":"server-state-changed","z":"8edb4e34.673db","name":"Tuesday Time","server":"9e74f251.0dfb4","version":1,"exposeToHomeAssistant":false,"haConfig":[{"property":"name","value":""},{"property":"icon","value":""}],"entityidfilter":"input_datetime.tuesday_time","entityidfiltertype":"exact","outputinitially":true,"state_type":"str","haltifstate":"","halt_if_type":"str","halt_if_compare":"is","outputs":1,"output_only_on_state_change":true,"for":0,"forType":"num","forUnits":"minutes","ignorePrevStateNull":false,"ignorePrevStateUnknown":false,"ignorePrevStateUnavailable":false,"ignoreCurrentStateUnknown":false,"ignoreCurrentStateUnavailable":false,"x":150,"y":320,"wires":[["d5fc3749.6d8148"]]},{"id":"10e9560a.40106a","type":"schedex","z":"8edb4e34.673db","name":"Tuesday","passthroughunhandled":false,"suspended":false,"lat":"","lon":"","ontime":"","ontopic":"","onpayload":"open","onoffset":0,"onrandomoffset":0,"offtime":"","offtopic":"","offpayload":"","offoffset":"60","offrandomoffset":0,"mon":false,"tue":true,"wed":false,"thu":false,"fri":false,"sat":false,"sun":false,"x":500,"y":300,"wires":[["b13ab16a.b4994"]]},{"id":"d5fc3749.6d8148","type":"function","z":"8edb4e34.673db","name":"Parse time","func":"new_msg = {\n    payload: {\n        ontime: msg.payload.substr(0,5),\n        offtime: msg.payload.substr(0,5)\n    }\n}\nreturn new_msg;","outputs":1,"noerr":0,"initialize":"","finalize":"","x":330,"y":320,"wires":[["10e9560a.40106a"]]},{"id":"78a2e03.fc9dc2","type":"server-state-changed","z":"8edb4e34.673db","name":"Wednesday Time","server":"9e74f251.0dfb4","version":1,"exposeToHomeAssistant":false,"haConfig":[{"property":"name","value":""},{"property":"icon","value":""}],"entityidfilter":"input_datetime.wednesday_time","entityidfiltertype":"exact","outputinitially":true,"state_type":"str","haltifstate":"","halt_if_type":"str","halt_if_compare":"is","outputs":1,"output_only_on_state_change":true,"for":0,"forType":"num","forUnits":"minutes","ignorePrevStateNull":false,"ignorePrevStateUnknown":false,"ignorePrevStateUnavailable":false,"ignoreCurrentStateUnknown":false,"ignoreCurrentStateUnavailable":false,"x":160,"y":440,"wires":[["80a2a78a.219648"]]},{"id":"43f9b7db.fd1088","type":"schedex","z":"8edb4e34.673db","name":"Wednesday","passthroughunhandled":false,"suspended":false,"lat":"","lon":"","ontime":"","ontopic":"","onpayload":"open","onoffset":0,"onrandomoffset":0,"offtime":"","offtopic":"","offpayload":"","offoffset":"60","offrandomoffset":0,"mon":false,"tue":false,"wed":true,"thu":false,"fri":false,"sat":false,"sun":false,"x":510,"y":420,"wires":[["b13ab16a.b4994"]]},{"id":"80a2a78a.219648","type":"function","z":"8edb4e34.673db","name":"Parse time","func":"new_msg = {\n    payload: {\n        ontime: msg.payload.substr(0,5),\n        offtime: msg.payload.substr(0,5)\n    }\n}\nreturn new_msg;","outputs":1,"noerr":0,"initialize":"","finalize":"","x":330,"y":440,"wires":[["43f9b7db.fd1088"]]},{"id":"ca04f4bb.0f2158","type":"server-state-changed","z":"8edb4e34.673db","name":"Thursday Time","server":"9e74f251.0dfb4","version":1,"exposeToHomeAssistant":false,"haConfig":[{"property":"name","value":""},{"property":"icon","value":""}],"entityidfilter":"input_datetime.thursday_time","entityidfiltertype":"exact","outputinitially":true,"state_type":"str","haltifstate":"","halt_if_type":"str","halt_if_compare":"is","outputs":1,"output_only_on_state_change":true,"for":0,"forType":"num","forUnits":"minutes","ignorePrevStateNull":false,"ignorePrevStateUnknown":false,"ignorePrevStateUnavailable":false,"ignoreCurrentStateUnknown":false,"ignoreCurrentStateUnavailable":false,"x":160,"y":560,"wires":[["30494bdf.f544e4"]]},{"id":"15df1791.0c2d88","type":"schedex","z":"8edb4e34.673db","name":"Thursday","passthroughunhandled":false,"suspended":false,"lat":"","lon":"","ontime":"","ontopic":"","onpayload":"open","onoffset":0,"onrandomoffset":0,"offtime":"","offtopic":"","offpayload":"","offoffset":"60","offrandomoffset":0,"mon":false,"tue":false,"wed":false,"thu":true,"fri":false,"sat":false,"sun":false,"x":500,"y":540,"wires":[["b13ab16a.b4994"]]},{"id":"30494bdf.f544e4","type":"function","z":"8edb4e34.673db","name":"Parse time","func":"new_msg = {\n    payload: {\n        ontime: msg.payload.substr(0,5),\n        offtime: msg.payload.substr(0,5)\n    }\n}\nreturn new_msg;","outputs":1,"noerr":0,"initialize":"","finalize":"","x":330,"y":560,"wires":[["15df1791.0c2d88"]]},{"id":"7fb0c4b4.cd63ac","type":"server-state-changed","z":"8edb4e34.673db","name":"Friday Time","server":"9e74f251.0dfb4","version":1,"exposeToHomeAssistant":false,"haConfig":[{"property":"name","value":""},{"property":"icon","value":""}],"entityidfilter":"input_datetime.friday_time","entityidfiltertype":"exact","outputinitially":true,"state_type":"str","haltifstate":"","halt_if_type":"str","halt_if_compare":"is","outputs":1,"output_only_on_state_change":true,"for":0,"forType":"num","forUnits":"minutes","ignorePrevStateNull":false,"ignorePrevStateUnknown":false,"ignorePrevStateUnavailable":false,"ignoreCurrentStateUnknown":false,"ignoreCurrentStateUnavailable":false,"x":150,"y":680,"wires":[["700fb46.5ae364c"]]},{"id":"da009f2c.186ea","type":"schedex","z":"8edb4e34.673db","name":"Friday","passthroughunhandled":false,"suspended":false,"lat":"","lon":"","ontime":"","ontopic":"","onpayload":"open","onoffset":0,"onrandomoffset":0,"offtime":"","offtopic":"","offpayload":"","offoffset":"60","offrandomoffset":0,"mon":false,"tue":false,"wed":false,"thu":false,"fri":true,"sat":false,"sun":false,"x":490,"y":660,"wires":[["b13ab16a.b4994"]]},{"id":"700fb46.5ae364c","type":"function","z":"8edb4e34.673db","name":"Parse time","func":"new_msg = {\n    payload: {\n        ontime: msg.payload.substr(0,5),\n        offtime: msg.payload.substr(0,5)\n    }\n}\nreturn new_msg;","outputs":1,"noerr":0,"initialize":"","finalize":"","x":330,"y":680,"wires":[["da009f2c.186ea"]]},{"id":"3fd96bc6.72e8e4","type":"server-state-changed","z":"8edb4e34.673db","name":"Saturday Time","server":"9e74f251.0dfb4","version":1,"exposeToHomeAssistant":false,"haConfig":[{"property":"name","value":""},{"property":"icon","value":""}],"entityidfilter":"input_datetime.saturday_time","entityidfiltertype":"exact","outputinitially":true,"state_type":"str","haltifstate":"","halt_if_type":"str","halt_if_compare":"is","outputs":1,"output_only_on_state_change":true,"for":0,"forType":"num","forUnits":"minutes","ignorePrevStateNull":false,"ignorePrevStateUnknown":false,"ignorePrevStateUnavailable":false,"ignoreCurrentStateUnknown":false,"ignoreCurrentStateUnavailable":false,"x":150,"y":800,"wires":[["9308f755.a50b48"]]},{"id":"64d8a7e.21bfa58","type":"schedex","z":"8edb4e34.673db","name":"Saturday","passthroughunhandled":false,"suspended":false,"lat":"","lon":"","ontime":"","ontopic":"","onpayload":"open","onoffset":0,"onrandomoffset":0,"offtime":"","offtopic":"","offpayload":"","offoffset":"60","offrandomoffset":0,"mon":false,"tue":false,"wed":false,"thu":false,"fri":false,"sat":true,"sun":false,"x":500,"y":780,"wires":[["b13ab16a.b4994"]]},{"id":"9308f755.a50b48","type":"function","z":"8edb4e34.673db","name":"Parse time","func":"new_msg = {\n    payload: {\n        ontime: msg.payload.substr(0,5),\n        offtime: msg.payload.substr(0,5)\n    }\n}\nreturn new_msg;","outputs":1,"noerr":0,"initialize":"","finalize":"","x":330,"y":800,"wires":[["64d8a7e.21bfa58"]]},{"id":"e56effa8.6acd3","type":"server-state-changed","z":"8edb4e34.673db","name":"Sunday Time","server":"9e74f251.0dfb4","version":1,"exposeToHomeAssistant":false,"haConfig":[{"property":"name","value":""},{"property":"icon","value":""}],"entityidfilter":"input_datetime.sunday_time","entityidfiltertype":"exact","outputinitially":true,"state_type":"str","haltifstate":"","halt_if_type":"str","halt_if_compare":"is","outputs":1,"output_only_on_state_change":true,"for":0,"forType":"num","forUnits":"minutes","ignorePrevStateNull":false,"ignorePrevStateUnknown":false,"ignorePrevStateUnavailable":false,"ignoreCurrentStateUnknown":false,"ignoreCurrentStateUnavailable":false,"x":150,"y":920,"wires":[["db8df76c.2e9178"]]},{"id":"88e631a0.04e1b","type":"schedex","z":"8edb4e34.673db","name":"Sunday","passthroughunhandled":false,"suspended":false,"lat":"","lon":"","ontime":"","ontopic":"","onpayload":"open","onoffset":0,"onrandomoffset":0,"offtime":"","offtopic":"","offpayload":"","offoffset":"60","offrandomoffset":0,"mon":false,"tue":false,"wed":false,"thu":false,"fri":false,"sat":false,"sun":true,"x":500,"y":900,"wires":[["b13ab16a.b4994"]]},{"id":"db8df76c.2e9178","type":"function","z":"8edb4e34.673db","name":"Parse time","func":"new_msg = {\n    payload: {\n        ontime: msg.payload.substr(0,5),\n        offtime: msg.payload.substr(0,5)\n    }\n}\nreturn new_msg;","outputs":1,"noerr":0,"initialize":"","finalize":"","x":330,"y":920,"wires":[["88e631a0.04e1b"]]},{"id":"d1ab8f99.4697a","type":"api-current-state","z":"8edb4e34.673db","name":"Percent open","server":"9e74f251.0dfb4","version":1,"outputs":1,"halt_if":"","halt_if_type":"str","halt_if_compare":"is","override_topic":false,"entity_id":"input_number.wake_percent","state_type":"num","state_location":"payload","override_payload":"msg","entity_location":"data","override_data":"msg","blockInputOverrides":false,"x":1030,"y":180,"wires":[["29565183.0e446e"]]},{"id":"32d54aa8.ad7716","type":"api-call-service","z":"8edb4e34.673db","name":"Set position","server":"9e74f251.0dfb4","version":1,"debugenabled":false,"service_domain":"cover","service":"set_cover_position","entityId":"cover.sonoff_1000d66ac3","data":"","dataType":"json","mergecontext":"","output_location":"payload","output_location_type":"msg","mustacheAltTags":false,"x":1130,"y":260,"wires":[[]]},{"id":"a5256955.748088","type":"api-call-service","z":"8edb4e34.673db","name":"","server":"9e74f251.0dfb4","version":1,"debugenabled":false,"service_domain":"cover","service":"open_cover","entityId":"cover.sonoff_1000d66886","data":"","dataType":"json","mergecontext":"","output_location":"","output_location_type":"none","mustacheAltTags":false,"x":940,"y":460,"wires":[["a32beccc.f6eb7"]]},{"id":"a32beccc.f6eb7","type":"api-call-service","z":"8edb4e34.673db","name":"","server":"9e74f251.0dfb4","version":1,"debugenabled":false,"service_domain":"cover","service":"open_cover","entityId":"cover.sonoff_1000d67323","data":"","dataType":"json","mergecontext":"","output_location":"","output_location_type":"none","mustacheAltTags":false,"x":940,"y":520,"wires":[["ce0cf6d1.5cd2a8"]]},{"id":"29565183.0e446e","type":"template","z":"8edb4e34.673db","name":"","field":"payload","fieldType":"msg","format":"handlebars","syntax":"mustache","template":"{\n  \"data\": {\n    \"entity_id\": \"cover.sonoff_1000d66ac3\",\n    \"position\": \"{{payload}}\"\n  }\n}","output":"str","x":1180,"y":180,"wires":[["32d54aa8.ad7716"]]},{"id":"8b86cf7c.b6db7","type":"api-call-service","z":"8edb4e34.673db","name":"Prime blinds","server":"9e74f251.0dfb4","version":1,"debugenabled":false,"service_domain":"input_boolean","service":"turn_on","entityId":"input_boolean.blinds_primed","data":"","dataType":"json","mergecontext":"","output_location":"","output_location_type":"none","mustacheAltTags":false,"x":950,"y":300,"wires":[[]]},{"id":"ce0cf6d1.5cd2a8","type":"api-call-service","z":"8edb4e34.673db","name":"Remove prime","server":"9e74f251.0dfb4","version":1,"debugenabled":false,"service_domain":"input_boolean","service":"turn_off","entityId":"input_boolean.blinds_primed","data":"","dataType":"json","mergecontext":"","output_location":"","output_location_type":"none","mustacheAltTags":false,"x":960,"y":580,"wires":[[]]},{"id":"e9e36859.a42df8","type":"api-call-service","z":"9af02288.f1339","name":"Turn on Cristo","server":"9e74f251.0dfb4","version":1,"debugenabled":false,"service_domain":"switch","service":"turn_on","entityId":"switch.cristo_lamp","data":"","dataType":"json","mergecontext":"","output_location":"","output_location_type":"none","mustacheAltTags":false,"x":760,"y":220,"wires":[["70753275.34db9c"]]},{"id":"70753275.34db9c","type":"delay","z":"9af02288.f1339","name":"","pauseType":"delay","timeout":"300","timeoutUnits":"seconds","rate":"1","nbRateUnits":"1","rateUnits":"second","randomFirst":"1","randomLast":"5","randomUnits":"seconds","drop":false,"x":770,"y":160,"wires":[["2bb48840.1488d8"]]},{"id":"2bb48840.1488d8","type":"api-call-service","z":"9af02288.f1339","name":"Turn off Cristo","server":"9e74f251.0dfb4","version":1,"debugenabled":false,"service_domain":"switch","service":"turn_off","entityId":"switch.cristo_lamp","data":"","dataType":"json","mergecontext":"","output_location":"","output_location_type":"none","mustacheAltTags":false,"x":960,"y":160,"wires":[[]]},{"id":"4e0c237e.9a22bc","type":"api-current-state","z":"9af02288.f1339","name":"If TV is off","server":"9e74f251.0dfb4","version":1,"outputs":2,"halt_if":"off","halt_if_type":"str","halt_if_compare":"is","override_topic":false,"entity_id":"media_player.living_room_tv","state_type":"str","state_location":"payload","override_payload":"msg","entity_location":"data","override_data":"msg","blockInputOverrides":false,"x":460,"y":160,"wires":[["24c2daab.4a1bd6"],[]]},{"id":"24c2daab.4a1bd6","type":"api-current-state","z":"9af02288.f1339","name":"Graeme lamp off","server":"9e74f251.0dfb4","version":1,"outputs":2,"halt_if":"false","halt_if_type":"bool","halt_if_compare":"is","override_topic":false,"entity_id":"light.graeme_s_lamp","state_type":"habool","state_location":"payload","override_payload":"msg","entity_location":"data","override_data":"msg","blockInputOverrides":false,"x":490,"y":240,"wires":[["73b4bef1.61ffa"],[]]},{"id":"73b4bef1.61ffa","type":"api-current-state","z":"9af02288.f1339","name":"Carol lamp off","server":"9e74f251.0dfb4","version":1,"outputs":2,"halt_if":"false","halt_if_type":"bool","halt_if_compare":"is","override_topic":false,"entity_id":"light.carol_s_lamp","state_type":"habool","state_location":"payload","override_payload":"msg","entity_location":"data","override_data":"msg","blockInputOverrides":false,"x":500,"y":320,"wires":[["48f90ace.780e54"],[]]},{"id":"48f90ace.780e54","type":"api-current-state","z":"9af02288.f1339","name":"Cristo lamp off","server":"9e74f251.0dfb4","version":1,"outputs":2,"halt_if":"false","halt_if_type":"bool","halt_if_compare":"is","override_topic":false,"entity_id":"switch.cristo_lamp","state_type":"habool","state_location":"payload","override_payload":"msg","entity_location":"data","override_data":"msg","blockInputOverrides":false,"x":540,"y":420,"wires":[["e9e36859.a42df8"],[]]},{"id":"7735a7c.fea0158","type":"trigger-state","z":"9af02288.f1339","name":"PIR","server":"9e74f251.0dfb4","exposeToHomeAssistant":false,"haConfig":[{"property":"name","value":""},{"property":"icon","value":""}],"entityid":"binary_sensor.living_room_pir_2","entityidfiltertype":"exact","debugenabled":false,"constraints":[{"targetType":"entity_id","targetValue":"sun.sun","propertyType":"current_state","comparatorType":"is","comparatorValueDatatype":"str","comparatorValue":"below_horizon","propertyValue":"new_state.state"}],"outputs":2,"customoutputs":[],"outputinitially":true,"state_type":"habool","x":250,"y":160,"wires":[["4e0c237e.9a22bc"],[]]},{"id":"23502929.d81ab6","type":"sun events","z":"9af02288.f1339","testmode":true,"verbose":true,"topic":"","name":"","x":260,"y":100,"wires":[["7735a7c.fea0158"]]},{"id":"53adddeb.6a7734","type":"api-call-service","z":"8edb4e34.673db","name":"","server":"9e74f251.0dfb4","version":1,"debugenabled":false,"service_domain":"notify","service":"mobile_app_iphone_de_ana_carolina","entityId":"","data":"{\"message\":\"{{payload}}\",\"title\":\"Wake up time changed\"}","dataType":"json","mergecontext":"","output_location":"","output_location_type":"none","mustacheAltTags":false,"x":800,"y":1380,"wires":[[]]},{"id":"2d595e49.8ea272","type":"server-state-changed","z":"8edb4e34.673db","name":"Monday On","server":"9e74f251.0dfb4","version":1,"exposeToHomeAssistant":false,"haConfig":[{"property":"name","value":""},{"property":"icon","value":""}],"entityidfilter":"input_boolean.monday_wake","entityidfiltertype":"exact","outputinitially":true,"state_type":"habool","haltifstate":"","halt_if_type":"str","halt_if_compare":"is","outputs":1,"output_only_on_state_change":true,"for":0,"forType":"num","forUnits":"minutes","ignorePrevStateNull":false,"ignorePrevStateUnknown":false,"ignorePrevStateUnavailable":false,"ignoreCurrentStateUnknown":false,"ignoreCurrentStateUnavailable":false,"x":150,"y":140,"wires":[["c35d7616.aa5588"]]},{"id":"c35d7616.aa5588","type":"function","z":"8edb4e34.673db","name":"Parse on/off","func":"new_msg = {\n    payload: {\n        mon: msg.payload,\n    }\n}\nreturn new_msg;","outputs":1,"noerr":0,"initialize":"","finalize":"","x":330,"y":140,"wires":[["3756e56e.8b317a"]]},{"id":"5366f97d.ddd608","type":"server-state-changed","z":"8edb4e34.673db","name":"Tuesday On","server":"9e74f251.0dfb4","version":1,"exposeToHomeAssistant":false,"haConfig":[{"property":"name","value":""},{"property":"icon","value":""}],"entityidfilter":"input_boolean.tuesday_wake","entityidfiltertype":"exact","outputinitially":true,"state_type":"habool","haltifstate":"","halt_if_type":"str","halt_if_compare":"is","outputs":1,"output_only_on_state_change":true,"for":0,"forType":"num","forUnits":"minutes","ignorePrevStateNull":false,"ignorePrevStateUnknown":false,"ignorePrevStateUnavailable":false,"ignoreCurrentStateUnknown":false,"ignoreCurrentStateUnavailable":false,"x":150,"y":260,"wires":[["8bfac80a.ae0c78"]]},{"id":"8bfac80a.ae0c78","type":"function","z":"8edb4e34.673db","name":"Parse on/off","func":"new_msg = {\n    payload: {\n        tue: msg.payload,\n    }\n}\nreturn new_msg;","outputs":1,"noerr":0,"initialize":"","finalize":"","x":330,"y":260,"wires":[["10e9560a.40106a"]]},{"id":"3fa31fcf.3ee28","type":"server-state-changed","z":"8edb4e34.673db","name":"Wednesday On","server":"9e74f251.0dfb4","version":1,"exposeToHomeAssistant":false,"haConfig":[{"property":"name","value":""},{"property":"icon","value":""}],"entityidfilter":"input_boolean.wednesday_wake","entityidfiltertype":"exact","outputinitially":true,"state_type":"habool","haltifstate":"","halt_if_type":"str","halt_if_compare":"is","outputs":1,"output_only_on_state_change":true,"for":0,"forType":"num","forUnits":"minutes","ignorePrevStateNull":false,"ignorePrevStateUnknown":false,"ignorePrevStateUnavailable":false,"ignoreCurrentStateUnknown":false,"ignoreCurrentStateUnavailable":false,"x":160,"y":380,"wires":[["efec16b7.7b4a88"]]},{"id":"efec16b7.7b4a88","type":"function","z":"8edb4e34.673db","name":"Parse on/off","func":"new_msg = {\n    payload: {\n        wed: msg.payload,\n    }\n}\nreturn new_msg;","outputs":1,"noerr":0,"initialize":"","finalize":"","x":330,"y":380,"wires":[["43f9b7db.fd1088"]]},{"id":"76d5f9f4.04c118","type":"server-state-changed","z":"8edb4e34.673db","name":"Thursday On","server":"9e74f251.0dfb4","version":1,"exposeToHomeAssistant":false,"haConfig":[{"property":"name","value":""},{"property":"icon","value":""}],"entityidfilter":"input_boolean.thursday_wake","entityidfiltertype":"exact","outputinitially":true,"state_type":"habool","haltifstate":"","halt_if_type":"str","halt_if_compare":"is","outputs":1,"output_only_on_state_change":true,"for":0,"forType":"num","forUnits":"minutes","ignorePrevStateNull":false,"ignorePrevStateUnknown":false,"ignorePrevStateUnavailable":false,"ignoreCurrentStateUnknown":false,"ignoreCurrentStateUnavailable":false,"x":150,"y":500,"wires":[["6e128ef1.182c1"]]},{"id":"6e128ef1.182c1","type":"function","z":"8edb4e34.673db","name":"Parse on/off","func":"new_msg = {\n    payload: {\n        thu: msg.payload,\n    }\n}\nreturn new_msg;","outputs":1,"noerr":0,"initialize":"","finalize":"","x":330,"y":500,"wires":[["15df1791.0c2d88"]]},{"id":"31f4235f.ab5a6c","type":"server-state-changed","z":"8edb4e34.673db","name":"Friday On","server":"9e74f251.0dfb4","version":1,"exposeToHomeAssistant":false,"haConfig":[{"property":"name","value":""},{"property":"icon","value":""}],"entityidfilter":"input_boolean.friday_wake","entityidfiltertype":"exact","outputinitially":true,"state_type":"habool","haltifstate":"","halt_if_type":"str","halt_if_compare":"is","outputs":1,"output_only_on_state_change":true,"for":0,"forType":"num","forUnits":"minutes","ignorePrevStateNull":false,"ignorePrevStateUnknown":false,"ignorePrevStateUnavailable":false,"ignoreCurrentStateUnknown":false,"ignoreCurrentStateUnavailable":false,"x":140,"y":620,"wires":[["c2ea7261.131cb"]]},{"id":"c2ea7261.131cb","type":"function","z":"8edb4e34.673db","name":"Parse on/off","func":"new_msg = {\n    payload: {\n        fri: msg.payload,\n    }\n}\nreturn new_msg;","outputs":1,"noerr":0,"initialize":"","finalize":"","x":330,"y":620,"wires":[["da009f2c.186ea"]]},{"id":"cc9de27f.3af81","type":"server-state-changed","z":"8edb4e34.673db","name":"Saturday On","server":"9e74f251.0dfb4","version":1,"exposeToHomeAssistant":false,"haConfig":[{"property":"name","value":""},{"property":"icon","value":""}],"entityidfilter":"input_boolean.saturday_wake","entityidfiltertype":"exact","outputinitially":true,"state_type":"habool","haltifstate":"","halt_if_type":"str","halt_if_compare":"is","outputs":1,"output_only_on_state_change":true,"for":0,"forType":"num","forUnits":"minutes","ignorePrevStateNull":false,"ignorePrevStateUnknown":false,"ignorePrevStateUnavailable":false,"ignoreCurrentStateUnknown":false,"ignoreCurrentStateUnavailable":false,"x":150,"y":740,"wires":[["f30b67fb.06d668"]]},{"id":"f30b67fb.06d668","type":"function","z":"8edb4e34.673db","name":"Parse on/off","func":"new_msg = {\n    payload: {\n        sat: msg.payload,\n    }\n}\nreturn new_msg;","outputs":1,"noerr":0,"initialize":"","finalize":"","x":330,"y":740,"wires":[["64d8a7e.21bfa58"]]},{"id":"4596e510.f6515c","type":"server-state-changed","z":"8edb4e34.673db","name":"Sunday On","server":"9e74f251.0dfb4","version":1,"exposeToHomeAssistant":false,"haConfig":[{"property":"name","value":""},{"property":"icon","value":""}],"entityidfilter":"input_boolean.sunday_wake","entityidfiltertype":"exact","outputinitially":true,"state_type":"habool","haltifstate":"","halt_if_type":"str","halt_if_compare":"is","outputs":1,"output_only_on_state_change":true,"for":0,"forType":"num","forUnits":"minutes","ignorePrevStateNull":false,"ignorePrevStateUnknown":false,"ignorePrevStateUnavailable":false,"ignoreCurrentStateUnknown":false,"ignoreCurrentStateUnavailable":false,"x":140,"y":860,"wires":[["45b3487e.054e98"]]},{"id":"45b3487e.054e98","type":"function","z":"8edb4e34.673db","name":"Parse on/off","func":"new_msg = {\n    payload: {\n        sun: msg.payload,\n    }\n}\nreturn new_msg;","outputs":1,"noerr":0,"initialize":"","finalize":"","x":330,"y":860,"wires":[["88e631a0.04e1b"]]},{"id":"8c08d874.5ac5d8","type":"server-state-changed","z":"8edb4e34.673db","name":"Monday Time","server":"9e74f251.0dfb4","version":1,"exposeToHomeAssistant":false,"haConfig":[{"property":"name","value":""},{"property":"icon","value":""}],"entityidfilter":"input_datetime.monday_time","entityidfiltertype":"exact","outputinitially":false,"state_type":"str","haltifstate":"","halt_if_type":"str","halt_if_compare":"is","outputs":1,"output_only_on_state_change":true,"for":"30","forType":"num","forUnits":"seconds","ignorePrevStateNull":false,"ignorePrevStateUnknown":false,"ignorePrevStateUnavailable":false,"ignoreCurrentStateUnknown":false,"ignoreCurrentStateUnavailable":false,"x":150,"y":1320,"wires":[["2e98d9bf.2b0306"]]},{"id":"65f0f6f4.6fbf48","type":"server-state-changed","z":"8edb4e34.673db","name":"Tuesday Time","server":"9e74f251.0dfb4","version":1,"exposeToHomeAssistant":false,"haConfig":[{"property":"name","value":""},{"property":"icon","value":""}],"entityidfilter":"input_datetime.tuesday_time","entityidfiltertype":"exact","outputinitially":false,"state_type":"str","haltifstate":"","halt_if_type":"str","halt_if_compare":"is","outputs":1,"output_only_on_state_change":true,"for":"30","forType":"num","forUnits":"seconds","ignorePrevStateNull":false,"ignorePrevStateUnknown":false,"ignorePrevStateUnavailable":false,"ignoreCurrentStateUnknown":false,"ignoreCurrentStateUnavailable":false,"x":150,"y":1360,"wires":[["c6650794.7103d8"]]},{"id":"a4f5e29a.767c1","type":"server-state-changed","z":"8edb4e34.673db","name":"Wednesday Time","server":"9e74f251.0dfb4","version":1,"exposeToHomeAssistant":false,"haConfig":[{"property":"name","value":""},{"property":"icon","value":""}],"entityidfilter":"input_datetime.wednesday_time","entityidfiltertype":"exact","outputinitially":false,"state_type":"str","haltifstate":"","halt_if_type":"str","halt_if_compare":"is","outputs":1,"output_only_on_state_change":true,"for":"30","forType":"num","forUnits":"seconds","ignorePrevStateNull":false,"ignorePrevStateUnknown":false,"ignorePrevStateUnavailable":false,"ignoreCurrentStateUnknown":false,"ignoreCurrentStateUnavailable":false,"x":160,"y":1400,"wires":[["a1efc805.431858"]]},{"id":"ad7a58d9.50ddd8","type":"server-state-changed","z":"8edb4e34.673db","name":"Thursday Time","server":"9e74f251.0dfb4","version":1,"exposeToHomeAssistant":false,"haConfig":[{"property":"name","value":""},{"property":"icon","value":""}],"entityidfilter":"input_datetime.thursday_time","entityidfiltertype":"exact","outputinitially":false,"state_type":"str","haltifstate":"","halt_if_type":"str","halt_if_compare":"is","outputs":1,"output_only_on_state_change":true,"for":"30","forType":"num","forUnits":"seconds","ignorePrevStateNull":false,"ignorePrevStateUnknown":false,"ignorePrevStateUnavailable":false,"ignoreCurrentStateUnknown":false,"ignoreCurrentStateUnavailable":false,"x":160,"y":1440,"wires":[["3039e5a.d865c1a"]]},{"id":"6d484aca.22a074","type":"server-state-changed","z":"8edb4e34.673db","name":"Friday Time","server":"9e74f251.0dfb4","version":1,"exposeToHomeAssistant":false,"haConfig":[{"property":"name","value":""},{"property":"icon","value":""}],"entityidfilter":"input_datetime.friday_time","entityidfiltertype":"exact","outputinitially":false,"state_type":"str","haltifstate":"","halt_if_type":"str","halt_if_compare":"is","outputs":1,"output_only_on_state_change":true,"for":"30","forType":"num","forUnits":"seconds","ignorePrevStateNull":false,"ignorePrevStateUnknown":false,"ignorePrevStateUnavailable":false,"ignoreCurrentStateUnknown":false,"ignoreCurrentStateUnavailable":false,"x":150,"y":1480,"wires":[["fe474eb9.584bd"]]},{"id":"38dce7f2.a44ed8","type":"server-state-changed","z":"8edb4e34.673db","name":"Saturday Time","server":"9e74f251.0dfb4","version":1,"exposeToHomeAssistant":false,"haConfig":[{"property":"name","value":""},{"property":"icon","value":""}],"entityidfilter":"input_datetime.saturday_time","entityidfiltertype":"exact","outputinitially":false,"state_type":"str","haltifstate":"","halt_if_type":"str","halt_if_compare":"is","outputs":1,"output_only_on_state_change":true,"for":"30","forType":"num","forUnits":"seconds","ignorePrevStateNull":false,"ignorePrevStateUnknown":false,"ignorePrevStateUnavailable":false,"ignoreCurrentStateUnknown":false,"ignoreCurrentStateUnavailable":false,"x":150,"y":1520,"wires":[["10ed65dc.42a9da"]]},{"id":"92cc858f.1d3858","type":"server-state-changed","z":"8edb4e34.673db","name":"Sunday Time","server":"9e74f251.0dfb4","version":1,"exposeToHomeAssistant":false,"haConfig":[{"property":"name","value":""},{"property":"icon","value":""}],"entityidfilter":"input_datetime.sunday_time","entityidfiltertype":"exact","outputinitially":false,"state_type":"str","haltifstate":"","halt_if_type":"str","halt_if_compare":"is","outputs":1,"output_only_on_state_change":true,"for":"30","forType":"num","forUnits":"seconds","ignorePrevStateNull":false,"ignorePrevStateUnknown":false,"ignorePrevStateUnavailable":false,"ignoreCurrentStateUnknown":false,"ignoreCurrentStateUnavailable":false,"x":150,"y":1560,"wires":[["c2ecbc01.cca04"]]},{"id":"eb85e483.4021b8","type":"server-state-changed","z":"8edb4e34.673db","name":"Monday On","server":"9e74f251.0dfb4","version":1,"exposeToHomeAssistant":false,"haConfig":[{"property":"name","value":""},{"property":"icon","value":""}],"entityidfilter":"input_boolean.monday_wake","entityidfiltertype":"exact","outputinitially":false,"state_type":"str","haltifstate":"","halt_if_type":"str","halt_if_compare":"is","outputs":1,"output_only_on_state_change":true,"for":"30","forType":"num","forUnits":"seconds","ignorePrevStateNull":false,"ignorePrevStateUnknown":false,"ignorePrevStateUnavailable":false,"ignoreCurrentStateUnknown":false,"ignoreCurrentStateUnavailable":false,"x":150,"y":1000,"wires":[["9f7025bb.679388"]]},{"id":"532f9455.7a63ec","type":"server-state-changed","z":"8edb4e34.673db","name":"Tuesday On","server":"9e74f251.0dfb4","version":1,"exposeToHomeAssistant":false,"haConfig":[{"property":"name","value":""},{"property":"icon","value":""}],"entityidfilter":"input_boolean.tuesday_wake","entityidfiltertype":"exact","outputinitially":false,"state_type":"str","haltifstate":"","halt_if_type":"str","halt_if_compare":"is","outputs":1,"output_only_on_state_change":true,"for":"30","forType":"num","forUnits":"seconds","ignorePrevStateNull":false,"ignorePrevStateUnknown":false,"ignorePrevStateUnavailable":false,"ignoreCurrentStateUnknown":false,"ignoreCurrentStateUnavailable":false,"x":150,"y":1040,"wires":[["e51dc888.4c37d8"]]},{"id":"7a73a186.38a68","type":"server-state-changed","z":"8edb4e34.673db","name":"Wednesday On","server":"9e74f251.0dfb4","version":1,"exposeToHomeAssistant":false,"haConfig":[{"property":"name","value":""},{"property":"icon","value":""}],"entityidfilter":"input_boolean.wednesday_wake","entityidfiltertype":"exact","outputinitially":false,"state_type":"str","haltifstate":"","halt_if_type":"str","halt_if_compare":"is","outputs":1,"output_only_on_state_change":true,"for":"30","forType":"num","forUnits":"seconds","ignorePrevStateNull":false,"ignorePrevStateUnknown":false,"ignorePrevStateUnavailable":false,"ignoreCurrentStateUnknown":false,"ignoreCurrentStateUnavailable":false,"x":160,"y":1080,"wires":[["fb660d02.1c546"]]},{"id":"d5ecc9f9.8be468","type":"server-state-changed","z":"8edb4e34.673db","name":"Thursday On","server":"9e74f251.0dfb4","version":1,"exposeToHomeAssistant":false,"haConfig":[{"property":"name","value":""},{"property":"icon","value":""}],"entityidfilter":"input_boolean.thursday_wake","entityidfiltertype":"exact","outputinitially":false,"state_type":"str","haltifstate":"","halt_if_type":"str","halt_if_compare":"is","outputs":1,"output_only_on_state_change":true,"for":"30","forType":"num","forUnits":"seconds","ignorePrevStateNull":false,"ignorePrevStateUnknown":false,"ignorePrevStateUnavailable":false,"ignoreCurrentStateUnknown":false,"ignoreCurrentStateUnavailable":false,"x":150,"y":1120,"wires":[["5fc3de84.10643"]]},{"id":"f058a2bf.9ee1d","type":"server-state-changed","z":"8edb4e34.673db","name":"Friday On","server":"9e74f251.0dfb4","version":1,"exposeToHomeAssistant":false,"haConfig":[{"property":"name","value":""},{"property":"icon","value":""}],"entityidfilter":"input_boolean.friday_wake","entityidfiltertype":"exact","outputinitially":false,"state_type":"str","haltifstate":"","halt_if_type":"str","halt_if_compare":"is","outputs":1,"output_only_on_state_change":true,"for":"30","forType":"num","forUnits":"seconds","ignorePrevStateNull":false,"ignorePrevStateUnknown":false,"ignorePrevStateUnavailable":false,"ignoreCurrentStateUnknown":false,"ignoreCurrentStateUnavailable":false,"x":140,"y":1160,"wires":[["be3bc235.7e4c2"]]},{"id":"1639f068.04d99","type":"server-state-changed","z":"8edb4e34.673db","name":"Saturday On","server":"9e74f251.0dfb4","version":1,"exposeToHomeAssistant":false,"haConfig":[{"property":"name","value":""},{"property":"icon","value":""}],"entityidfilter":"input_boolean.saturday_wake","entityidfiltertype":"exact","outputinitially":false,"state_type":"str","haltifstate":"","halt_if_type":"str","halt_if_compare":"is","outputs":1,"output_only_on_state_change":true,"for":"30","forType":"num","forUnits":"seconds","ignorePrevStateNull":false,"ignorePrevStateUnknown":false,"ignorePrevStateUnavailable":false,"ignoreCurrentStateUnknown":false,"ignoreCurrentStateUnavailable":false,"x":150,"y":1200,"wires":[["b35c9aa5.9690e8"]]},{"id":"d8b2b07d.ce707","type":"server-state-changed","z":"8edb4e34.673db","name":"Sunday On","server":"9e74f251.0dfb4","version":1,"exposeToHomeAssistant":false,"haConfig":[{"property":"name","value":""},{"property":"icon","value":""}],"entityidfilter":"input_boolean.sunday_wake","entityidfiltertype":"exact","outputinitially":false,"state_type":"str","haltifstate":"","halt_if_type":"str","halt_if_compare":"is","outputs":1,"output_only_on_state_change":true,"for":"30","forType":"num","forUnits":"seconds","ignorePrevStateNull":false,"ignorePrevStateUnknown":false,"ignorePrevStateUnavailable":false,"ignoreCurrentStateUnknown":false,"ignoreCurrentStateUnavailable":false,"x":140,"y":1240,"wires":[["d9f77ba9.4653c8"]]},{"id":"2e98d9bf.2b0306","type":"template","z":"8edb4e34.673db","name":"","field":"payload","fieldType":"msg","format":"handlebars","syntax":"mustache","template":"Monday: {{payload}}","output":"str","x":320,"y":1320,"wires":[["35a9f997.3bf006"]]},{"id":"c6650794.7103d8","type":"template","z":"8edb4e34.673db","name":"","field":"payload","fieldType":"msg","format":"handlebars","syntax":"mustache","template":"Tuesday: {{payload}}","output":"str","x":320,"y":1360,"wires":[["35a9f997.3bf006"]]},{"id":"a1efc805.431858","type":"template","z":"8edb4e34.673db","name":"","field":"payload","fieldType":"msg","format":"handlebars","syntax":"mustache","template":"Wednesday: {{payload}}","output":"str","x":320,"y":1400,"wires":[["35a9f997.3bf006"]]},{"id":"3039e5a.d865c1a","type":"template","z":"8edb4e34.673db","name":"","field":"payload","fieldType":"msg","format":"handlebars","syntax":"mustache","template":"Thursday: {{payload}}","output":"str","x":320,"y":1440,"wires":[["35a9f997.3bf006"]]},{"id":"fe474eb9.584bd","type":"template","z":"8edb4e34.673db","name":"","field":"payload","fieldType":"msg","format":"handlebars","syntax":"mustache","template":"Friday: {{payload}}","output":"str","x":320,"y":1480,"wires":[["35a9f997.3bf006"]]},{"id":"10ed65dc.42a9da","type":"template","z":"8edb4e34.673db","name":"","field":"payload","fieldType":"msg","format":"handlebars","syntax":"mustache","template":"Saturday: {{payload}}","output":"str","x":320,"y":1520,"wires":[["35a9f997.3bf006"]]},{"id":"c2ecbc01.cca04","type":"template","z":"8edb4e34.673db","name":"","field":"payload","fieldType":"msg","format":"handlebars","syntax":"mustache","template":"Sunday: {{payload}}","output":"str","x":320,"y":1560,"wires":[["35a9f997.3bf006"]]},{"id":"35a9f997.3bf006","type":"join","z":"8edb4e34.673db","name":"","mode":"custom","build":"string","property":"payload","propertyType":"msg","key":"topic","joiner":" | ","joinerType":"str","accumulate":false,"timeout":"30","count":"","reduceRight":false,"reduceExp":"","reduceInit":"","reduceInitType":"","reduceFixup":"","x":520,"y":1380,"wires":[["53adddeb.6a7734","96aa1693.fc0b08"]]},{"id":"3e751745.38fd58","type":"api-call-service","z":"8edb4e34.673db","name":"","server":"9e74f251.0dfb4","version":1,"debugenabled":false,"service_domain":"notify","service":"mobile_app_iphone_de_ana_carolina","entityId":"","data":"{\"message\":\"{{payload}}\",\"title\":\"Wake up turned on/off\"}","dataType":"json","mergecontext":"","output_location":"","output_location_type":"none","mustacheAltTags":false,"x":800,"y":1060,"wires":[[]]},{"id":"9f7025bb.679388","type":"template","z":"8edb4e34.673db","name":"","field":"payload","fieldType":"msg","format":"handlebars","syntax":"mustache","template":"Monday: {{payload}}","output":"str","x":320,"y":1000,"wires":[["fb3c4458.6d14e8"]]},{"id":"e51dc888.4c37d8","type":"template","z":"8edb4e34.673db","name":"","field":"payload","fieldType":"msg","format":"handlebars","syntax":"mustache","template":"Tuesday: {{payload}}","output":"str","x":320,"y":1040,"wires":[["fb3c4458.6d14e8"]]},{"id":"fb660d02.1c546","type":"template","z":"8edb4e34.673db","name":"","field":"payload","fieldType":"msg","format":"handlebars","syntax":"mustache","template":"Wednesday: {{payload}}","output":"str","x":320,"y":1080,"wires":[["fb3c4458.6d14e8"]]},{"id":"5fc3de84.10643","type":"template","z":"8edb4e34.673db","name":"","field":"payload","fieldType":"msg","format":"handlebars","syntax":"mustache","template":"Thursday: {{payload}}","output":"str","x":320,"y":1120,"wires":[["fb3c4458.6d14e8"]]},{"id":"be3bc235.7e4c2","type":"template","z":"8edb4e34.673db","name":"","field":"payload","fieldType":"msg","format":"handlebars","syntax":"mustache","template":"Friday: {{payload}}","output":"str","x":320,"y":1160,"wires":[["fb3c4458.6d14e8"]]},{"id":"b35c9aa5.9690e8","type":"template","z":"8edb4e34.673db","name":"","field":"payload","fieldType":"msg","format":"handlebars","syntax":"mustache","template":"Saturday: {{payload}}","output":"str","x":320,"y":1200,"wires":[["fb3c4458.6d14e8"]]},{"id":"d9f77ba9.4653c8","type":"template","z":"8edb4e34.673db","name":"","field":"payload","fieldType":"msg","format":"handlebars","syntax":"mustache","template":"Sunday: {{payload}}","output":"str","x":320,"y":1240,"wires":[["fb3c4458.6d14e8"]]},{"id":"fb3c4458.6d14e8","type":"join","z":"8edb4e34.673db","name":"","mode":"custom","build":"string","property":"payload","propertyType":"msg","key":"topic","joiner":" | ","joinerType":"str","accumulate":false,"timeout":"30","count":"","reduceRight":false,"reduceExp":"","reduceInit":"","reduceInitType":"","reduceFixup":"","x":520,"y":1060,"wires":[["3e751745.38fd58","2163cff3.4feef"]]},{"id":"2163cff3.4feef","type":"api-call-service","z":"8edb4e34.673db","name":"","server":"9e74f251.0dfb4","version":1,"debugenabled":false,"service_domain":"notify","service":"mobile_app_mi_9_lite","entityId":"","data":"{\"message\":\"{{payload}}\",\"title\":\"Wake up turned on/off\"}","dataType":"json","mergecontext":"","output_location":"","output_location_type":"none","mustacheAltTags":false,"x":750,"y":1120,"wires":[[]]},{"id":"96aa1693.fc0b08","type":"api-call-service","z":"8edb4e34.673db","name":"","server":"9e74f251.0dfb4","version":1,"debugenabled":false,"service_domain":"notify","service":"mobile_app_mi_9_lite","entityId":"","data":"{\"message\":\"{{payload}}\",\"title\":\"Wake up time changed\"}","dataType":"json","mergecontext":"","output_location":"","output_location_type":"none","mustacheAltTags":false,"x":750,"y":1440,"wires":[[]]},{"id":"f0fb485f.0caa78","type":"trigger-state","z":"8edb4e34.673db","name":"PIR","server":"9e74f251.0dfb4","exposeToHomeAssistant":false,"haConfig":[{"property":"name","value":""},{"property":"icon","value":""}],"entityid":"binary_sensor.living_room_pir_2","entityidfiltertype":"exact","debugenabled":false,"constraints":[{"targetType":"entity_id","targetValue":"input_boolean.blinds_primed","propertyType":"current_state","comparatorType":"is","comparatorValueDatatype":"str","comparatorValue":"on","propertyValue":"new_state.state"}],"outputs":2,"customoutputs":[],"outputinitially":true,"state_type":"habool","x":890,"y":380,"wires":[["a5256955.748088"],[]]},{"id":"c05f9ab3.f7cbc8","type":"schedex","z":"8d2a5b3.c3ffca8","name":"Night clean","passthroughunhandled":false,"suspended":false,"lat":"41.181","lon":"-8.623","ontime":"11:28","ontopic":"","onpayload":"Silent","onoffset":0,"onrandomoffset":0,"offtime":"11:29","offtopic":"","offpayload":"Standard","offoffset":"","offrandomoffset":0,"mon":true,"tue":true,"wed":true,"thu":true,"fri":true,"sat":true,"sun":true,"x":150,"y":140,"wires":[["48c2db30.6aacd4"]]},{"id":"6d9491c7.f757c","type":"api-call-service","z":"8d2a5b3.c3ffca8","name":"Night Areas","server":"9e74f251.0dfb4","version":1,"debugenabled":false,"service_domain":"xiaomi_miio","service":"vacuum_clean_segment","entityId":"vacuum.roborock_s5_max","data":"{\"segments\":[16,19]}","dataType":"json","mergecontext":"","output_location":"","output_location_type":"none","mustacheAltTags":false,"x":930,"y":140,"wires":[[]]},{"id":"47b1984a.1a2538","type":"comment","z":"8d2a5b3.c3ffca8","name":"Segment codes","info":"16: Kitchen \n17: Bedroom \n18: Null\n19: Living room \n20: Hall \n21: Bathroom ","x":160,"y":400,"wires":[]},{"id":"edb9f20e.ae294","type":"schedex","z":"8d2a5b3.c3ffca8","name":"Day clean (week)","passthroughunhandled":false,"suspended":false,"lat":"41.181","lon":"-8.623","ontime":"09:00","ontopic":"","onpayload":"start","onoffset":0,"onrandomoffset":0,"offtime":"09:01","offtopic":"","offpayload":"","offoffset":0,"offrandomoffset":0,"mon":false,"tue":true,"wed":false,"thu":true,"fri":false,"sat":false,"sun":false,"x":170,"y":240,"wires":[["ea7c8a25.1f7b88"]]},{"id":"c38dfec6.120bb","type":"api-call-service","z":"8d2a5b3.c3ffca8","name":"Day Areas","server":"9e74f251.0dfb4","version":1,"debugenabled":false,"service_domain":"xiaomi_miio","service":"vacuum_clean_segment","entityId":"vacuum.roborock_s5_max","data":"{\"data\":{\"segments\":\"[17, 20, 21]\"}}","dataType":"json","mergecontext":"","output_location":"","output_location_type":"none","mustacheAltTags":false,"x":730,"y":240,"wires":[[]]},{"id":"d27232c5.916f5","type":"schedex","z":"8d2a5b3.c3ffca8","name":"Day clean (weekend)","passthroughunhandled":false,"suspended":false,"lat":"41.181","lon":"-8.623","ontime":"10:00","ontopic":"","onpayload":"start","onoffset":0,"onrandomoffset":0,"offtime":"10:01","offtopic":"","offpayload":"","offoffset":0,"offrandomoffset":0,"mon":false,"tue":false,"wed":false,"thu":false,"fri":false,"sat":true,"sun":false,"x":180,"y":300,"wires":[["ea7c8a25.1f7b88"]]},{"id":"48c2db30.6aacd4","type":"api-call-service","z":"8d2a5b3.c3ffca8","name":"Fan speed","server":"9e74f251.0dfb4","version":1,"debugenabled":false,"service_domain":"vacuum","service":"set_fan_speed","entityId":"vacuum.roborock_s5_max","data":"{\"fan_speed\":\"{{payload}}\"}","dataType":"json","mergecontext":"","output_location":"","output_location_type":"none","mustacheAltTags":false,"x":390,"y":140,"wires":[["d1e2e036.3e1e2"]]},{"id":"43357684.fdc1c8","type":"delay","z":"8d2a5b3.c3ffca8","name":"","pauseType":"delay","timeout":"5","timeoutUnits":"seconds","rate":"1","nbRateUnits":"1","rateUnits":"second","randomFirst":"1","randomLast":"5","randomUnits":"seconds","drop":false,"x":740,"y":140,"wires":[["6d9491c7.f757c"]]},{"id":"d1e2e036.3e1e2","type":"switch","z":"8d2a5b3.c3ffca8","name":"","property":"payload","propertyType":"msg","rules":[{"t":"eq","v":"Silent","vt":"str"}],"checkall":"true","repair":false,"outputs":1,"x":570,"y":140,"wires":[["43357684.fdc1c8"]]},{"id":"ea7c8a25.1f7b88","type":"switch","z":"8d2a5b3.c3ffca8","name":"","property":"payload","propertyType":"msg","rules":[{"t":"eq","v":"start","vt":"str"}],"checkall":"true","repair":false,"outputs":1,"x":490,"y":240,"wires":[["c38dfec6.120bb"]]},{"id":"b13ab16a.b4994","type":"switch","z":"8edb4e34.673db","name":"","property":"payload","propertyType":"msg","rules":[{"t":"eq","v":"open","vt":"str"}],"checkall":"true","repair":false,"outputs":1,"x":850,"y":180,"wires":[["8b86cf7c.b6db7","d1ab8f99.4697a"]]}]